[
  {
    "date": "02/07/2026",
    "time": "13:30",
    "event": "Initial Jobless Claims"
  },
  {
    "date": "02/07/2026",
    "time": "13:30",
    "event": "Nonfarm Payrolls  (Jun)"
  },
  {
    "date": "02/07/2026",
    "time": "13:30",
    "event": "Unemployment Rate  (Jun)"
  },
  {
    "date": "06/07/2026",
    "time": "15:00",
    "event": "ISM Non-Manufacturing PMI  (Jun)"
  },
  {
    "date": "06/07/2026",
    "time": "15:00",
    "event": "ISM Non-Manufacturing Prices  (Jun)"
  },
  {
    "date": "08/07/2026",
    "time": "19:00",
    "event": "FOMC Meeting Minutes"
  },
  {
    "date": "09/07/2026",
    "time": "13:30",
    "event": "Initial Jobless Claims"
  }
]